prueba_paquete/__init__.py
prueba_paquete/classification.py
prueba_paquete/clustering.py
prueba_paquete/concept_extraction.py
prueba_paquete/sentiment_analysis.py
prueba_paquete/utils.py
prueba_paquete/lexicon_lib/MLsenticon.es.xml
prueba_paquete/lexicon_lib/lemmatization-es.txt
prueba_paquete/lexicon_lib/new_neg_words.txt
prueba_paquete/lexicon_lib/new_pos_words.txt
prueba_paquete-0.1.7.dist-info/DESCRIPTION.rst
prueba_paquete-0.1.7.dist-info/METADATA
prueba_paquete-0.1.7.dist-info/RECORD
prueba_paquete-0.1.7.dist-info/WHEEL
prueba_paquete-0.1.7.dist-info/metadata.json
prueba_paquete-0.1.7.dist-info/top_level.txt
